odoo/addons/iot_template_oca/README.rst
odoo/addons/iot_template_oca/__init__.py
odoo/addons/iot_template_oca/__manifest__.py
odoo/addons/iot_template_oca/controller/__init__.py
odoo/addons/iot_template_oca/controller/iot_controller.py
odoo/addons/iot_template_oca/demo/iot_template.xml
odoo/addons/iot_template_oca/i18n/es.po
odoo/addons/iot_template_oca/i18n/fa.po
odoo/addons/iot_template_oca/i18n/iot_template_oca.pot
odoo/addons/iot_template_oca/i18n/it.po
odoo/addons/iot_template_oca/models/__init__.py
odoo/addons/iot_template_oca/models/iot_device.py
odoo/addons/iot_template_oca/models/iot_device_input.py
odoo/addons/iot_template_oca/models/iot_device_output.py
odoo/addons/iot_template_oca/models/iot_template.py
odoo/addons/iot_template_oca/readme/CONTRIBUTORS.md
odoo/addons/iot_template_oca/readme/DESCRIPTION.md
odoo/addons/iot_template_oca/readme/USAGE.md
odoo/addons/iot_template_oca/security/ir.model.access.csv
odoo/addons/iot_template_oca/static/description/icon.png
odoo/addons/iot_template_oca/static/description/index.html
odoo/addons/iot_template_oca/tests/__init__.py
odoo/addons/iot_template_oca/tests/test_iot_template.py
odoo/addons/iot_template_oca/views/iot_template_views.xml
odoo/addons/iot_template_oca/wizards/__init__.py
odoo/addons/iot_template_oca/wizards/iot_device_configure.py
odoo/addons/iot_template_oca/wizards/iot_device_configure.xml
odoo_addon_iot_template_oca-17.0.1.0.0.2.dist-info/METADATA
odoo_addon_iot_template_oca-17.0.1.0.0.2.dist-info/WHEEL
odoo_addon_iot_template_oca-17.0.1.0.0.2.dist-info/top_level.txt
odoo_addon_iot_template_oca-17.0.1.0.0.2.dist-info/RECORD
